django_app_graphql/GraphQLSection.py
django_app_graphql/__init__.py
django_app_graphql/admin.py
django_app_graphql/apps.py
django_app_graphql/conf.py
django_app_graphql/middleware.py
django_app_graphql/models.py
django_app_graphql/tests.py
django_app_graphql/urls.py
django_app_graphql/validators.py
django_app_graphql/version.py
django_app_graphql/views.py
django_app_graphql/ariadne/AbstractScalarType.py
django_app_graphql/ariadne/__init__.py
django_app_graphql/ariadne/decorators.py
django_app_graphql/ariadne/scalars.py
django_app_graphql/ariadne/schema.py
django_app_graphql/data/graphql/ariadne/scalars.graphql
django_app_graphql/graphene/AbstractGraphQLError.py
django_app_graphql/graphene/AbstractUploadMutationCreator.py
django_app_graphql/graphene/GrapheneClient.py
django_app_graphql/graphene/IUploadMutationCreator.py
django_app_graphql/graphene/__init__.py
django_app_graphql/graphene/schema.py
django_app_graphql/graphene/uploaders.py
django_app_graphql/graphene/graphqls/__init__.py
django_app_graphql/graphene/tests/AbstractGraphQLTestMixin.py
django_app_graphql/graphene/tests/__init__.py
django_app_graphql/graphene/tests/testcases.py
django_app_graphql/migrations/__init__.py
django_app_graphql-1.30.14.dist-info/LICENSE.md
django_app_graphql-1.30.14.dist-info/METADATA
django_app_graphql-1.30.14.dist-info/WHEEL
django_app_graphql-1.30.14.dist-info/top_level.txt
django_app_graphql-1.30.14.dist-info/RECORD
