Metadata-Version: 2.1
Name: django-app-graphql
Version: 1.30.14
Summary: Some stuff that i used when developing with django
Home-page: https://github.com/Koldar/django-koldar-common-apps
Author: Massimo Bono
Author-email: massimobono1@gmail.com
License: MIT
Keywords: utils
Platform: UNKNOWN
Classifier: Programming Language :: Python :: 3
Classifier: Operating System :: OS Independent
Requires-Python: >=3.6
License-File: LICENSE.md
License-File: Makefile
License-File: PMakeupfile.py
License-File: README.md
License-File: TWINE_PYPI_PASSWORD
License-File: make.bat
License-File: pmakeup-cache.json
License-File: requirements.txt
License-File: setup.py
Requires-Dist: aniso8601 (>=8.1.1)
Requires-Dist: arrow (>=1.1.0)
Requires-Dist: Django (>=3.2.4)
Requires-Dist: django-appconf (>=1.0.4)
Requires-Dist: django-currentuser (>=0.5.3)
Requires-Dist: django-koldar-utils (>=2.8.1)
Requires-Dist: django-polymorphic (>=3.0.0)
Requires-Dist: graphene (>=3.0b7)
Requires-Dist: graphene-django (>=3.0.0b7)
Requires-Dist: graphene-django-extras (>=0.5.1)
Requires-Dist: graphql-core (>=3.1.5)
Requires-Dist: jsonpath-ng (>=1.5.2)
Requires-Dist: pydot (>=1.4.2)
Requires-Dist: stringcase (>=1.2.0)
Requires-Dist: graphene-file-upload (>=1.3.0)
Requires-Dist: semantic-version (>=2.8.5)
Requires-Dist: gql (>=3.0.0a6)
Provides-Extra: docs
Requires-Dist: sphinx ; extra == 'docs'
Requires-Dist: sphinx-rtd-theme ; extra == 'docs'
Provides-Extra: test
Requires-Dist: pytest ; extra == 'test'
Requires-Dist: mock ; extra == 'test'
